usd_rerun_logger/__init__.py
usd_rerun_logger/env_wrapper.py
usd_rerun_logger/isaac_lab_logger.py
usd_rerun_logger/mesh.py
usd_rerun_logger/prim.py
usd_rerun_logger/py.typed
usd_rerun_logger/shader.py
usd_rerun_logger/transfom.py
usd_rerun_logger/usd_logger.py
usd_rerun_logger/util.py
usd_rerun_logger/visual.py
usd_rerun_logger-0.4.0.dist-info/WHEEL
usd_rerun_logger-0.4.0.dist-info/METADATA
usd_rerun_logger-0.4.0.dist-info/RECORD
