Metadata-Version: 2.3
Name: usd-rerun-logger
Version: 0.4.0
Summary: Python package for visualizing OpenUSD based simulations (like NVIDIA Isaac Sim) with Rerun.io
Keywords: USD,OpenUSD,Rerun,visualization,Isaac Sim,Isaac Lab,Omniverse
Author: AGC, TN
Author-email: AGC <andras@artefacts.com>, TN <tomo@artefacts.com>
License: MIT
Classifier: Development Status :: 3 - Alpha
Classifier: Intended Audience :: Developers
Classifier: License :: OSI Approved :: MIT License
Classifier: Programming Language :: Python :: 3
Classifier: Programming Language :: Python :: 3.11
Classifier: Operating System :: OS Independent
Classifier: Topic :: Scientific/Engineering
Classifier: Typing :: Typed
Requires-Dist: gymnasium[other]>=1.2.3
Requires-Dist: pillow>=11.2.1
Requires-Dist: rerun-sdk>=0.23.1
Requires-Python: >=3.11
Project-URL: Homepage, https://github.com/art-e-fact/usd-rerun-logger
Project-URL: Issues, https://github.com/art-e-fact/usd-rerun-logger/issues
Project-URL: Source, https://github.com/art-e-fact/usd-rerun-logger
